django_limits/__init__.py
django_limits/apps.py
django_limits/exceptions.py
django_limits/limiter.py
django_limits/middleware.py
django_limits/signals.py
django_limits/views.py
django_limits/templates/django_limits/limit_exceeded.html
django_limits/tests/__init__.py
django_limits/tests/limiter.py
django_limits/tests/models.py
django_limits/tests/settings.py
django_limits/tests/tests.py
django_limits-0.0.6.dist-info/LICENSE
django_limits-0.0.6.dist-info/METADATA
django_limits-0.0.6.dist-info/WHEEL
django_limits-0.0.6.dist-info/top_level.txt
django_limits-0.0.6.dist-info/RECORD
