Metadata-Version: 1.1
Name: django-limits
Version: 0.0.6
Summary: UNKNOWN
Home-page: https://github.com/LegoStormtroopr/django-limits/
Author: Samuel Spencer
Author-email: sam@aristotlemetadata.com
License: GPLv3 License
Keywords: django limit objects
Platform: UNKNOWN
Classifier: Environment :: Web Environment
Classifier: Framework :: Django
Classifier: Intended Audience :: Developers
Classifier: License :: OSI Approved :: GNU General Public License (GPL)
Classifier: Operating System :: OS Independent
Classifier: Programming Language :: Python
Classifier: Programming Language :: Python
Classifier: Programming Language :: Python :: 2
Classifier: Programming Language :: Python :: 2.6
Classifier: Programming Language :: Python :: 2.7
Classifier: Programming Language :: Python :: 3
Classifier: Programming Language :: Python :: 3.2
Classifier: Programming Language :: Python :: 3.3
Classifier: Programming Language :: Python :: 3.4
Classifier: Topic :: Utilities
Classifier: Topic :: Internet :: WWW/HTTP
